intelli_sms_gateway/__init__.py
intelli_sms_gateway/client.py
intelli_sms_gateway-0.1.6.dist-info/LICENSE
intelli_sms_gateway-0.1.6.dist-info/METADATA
intelli_sms_gateway-0.1.6.dist-info/WHEEL
intelli_sms_gateway-0.1.6.dist-info/top_level.txt
intelli_sms_gateway-0.1.6.dist-info/RECORD
