Metadata-Version: 2.1
Name: intelli-sms-gateway
Version: 0.1.6
Summary: A package extending developable features of the Intelli-Africa Solutions SMS Gateway
Home-page: UNKNOWN
Author: Intelli Africa Solutions
Author-email: info@intelliafrica.solutions
License: MIT
Platform: UNKNOWN
Classifier: Programming Language :: Python :: 3
Classifier: License :: OSI Approved :: MIT License
Classifier: Operating System :: OS Independent
Requires-Python: >=3.6
License-File: LICENSE
